ns2json/__about__.py
ns2json/__init__.py
ns2json/__main__.py
ns2json/ns2json.py
ns2json/dns/__init__.py
ns2json/dns/clean_raw_data.py
ns2json/dns/format_data.py
ns2json/dns/pull_data.py
ns2json/dns/type_a.py
ns2json/dns/type_aaaa.py
ns2json/dns/type_mx.py
ns2json/dns/type_ns.py
ns2json/dns/type_soa.py
ns2json/dns/type_txt.py
ns2json/utils/__init__.py
ns2json/utils/check_sys.py
ns2json/utils/export_data.py
ns2json/utils/get_set_args.py
ns2json-1.1.0b0.dist-info/METADATA
ns2json-1.1.0b0.dist-info/WHEEL
ns2json-1.1.0b0.dist-info/entry_points.txt
ns2json-1.1.0b0.dist-info/licenses/LICENSE
ns2json-1.1.0b0.dist-info/RECORD
