Metadata-Version: 2.1
Name: ns2json
Version: 1.1.0b0
Summary: A Python script to converts and saves a data from a DNS response to a JSON file.
Project-URL: Repository, https://github.com/drazkgi/ns2json
Author-email: Bartłomiej Drążkiewicz <bartlomiej@drazkiewicz.me>
License-Expression: MIT
License-File: LICENSE
Keywords: convert,dns,file,json,mit,python,script
Classifier: Development Status :: 4 - Beta
Classifier: Environment :: Console
Classifier: License :: OSI Approved :: MIT License
Classifier: Operating System :: Microsoft :: Windows
Classifier: Programming Language :: Python :: 3
Classifier: Topic :: File Formats :: JSON
Classifier: Topic :: Internet :: Name Service (DNS)
Classifier: Topic :: System :: Networking
Requires-Python: >=3.10
